cellector/__init__.py
cellector/features.py
cellector/filters.py
cellector/manager.py
cellector/roi_processor.py
cellector/utils.py
cellector/gui/__init__.py
cellector/gui/_gui_split_by_plane.py
cellector/gui/gui.py
cellector/gui/utils.py
cellector/io/__init__.py
cellector/io/base.py
cellector/io/constructing.py
cellector/io/operations.py
cellector-2.0.3.dist-info/METADATA
cellector-2.0.3.dist-info/WHEEL
cellector-2.0.3.dist-info/licenses/LICENSE
cellector-2.0.3.dist-info/RECORD
