Metadata-Version: 2.4
Name: cellector
Version: 2.0.3
Summary: A pipeline and GUI for determining which ROIs match features in a fluorescence image.
Project-URL: Homepage, https://github.com/landoskape/cellector
Project-URL: Bug Tracker, https://github.com/landoskape/cellector/issues
Author: Andrew T. Landau
Author-email: andrewtylerlandau@gmaildot.com
License-File: LICENSE
Keywords: GUI,ROI,cell,feature,fluorescence,image,matching,pipeline
Requires-Python: >=3.7
Requires-Dist: matplotlib
Requires-Dist: napari[all]
Requires-Dist: numba
Requires-Dist: numpy>=1.24
Requires-Dist: pyqt5
Requires-Dist: pyqtgraph
Requires-Dist: scipy
Requires-Dist: tqdm
Provides-Extra: test
Requires-Dist: pytest; extra == 'test'
Requires-Dist: pytest-cov; extra == 'test'
